cli/__init__.py
cli/color.py
cli/controller.py
cli/editor.py
cli/error.py
cli/main.py
cli/model.py
cli/view.py
curses_wrapper/__init__.py
curses_wrapper/color.py
curses_wrapper/scroll_manager.py
curses_wrapper/textbox.py
kafka_wrapper/__init__.py
kafka_wrapper/acl.py
kafka_wrapper/broker.py
kafka_wrapper/consume.py
kafka_wrapper/consumer_group.py
kafka_wrapper/kafka_resource.py
kafka_wrapper/partition.py
kafka_wrapper/producer.py
kafka_wrapper/topic.py
k4-0.1.0a0.dist-info/LICENSE
k4-0.1.0a0.dist-info/WHEEL
k4-0.1.0a0.dist-info/entry_points.txt
k4-0.1.0a0.dist-info/METADATA
k4-0.1.0a0.dist-info/RECORD
