Metadata-Version: 2.1
Name: k4
Version: 0.1.0a0
Summary: A command line tool for controlling and interacting with Kafka.
Home-page: https://github.com/aidanmelen/k4
License: MIT
Author: Aidan Melen
Author-email: aidan-melen@protonmail.com
Requires-Python: >=3.11,<4.0
Classifier: License :: OSI Approved :: MIT License
Classifier: Programming Language :: Python :: 3
Classifier: Programming Language :: Python :: 3.11
Requires-Dist: confluent-kafka (>=2.0.2,<3.0.0)
Requires-Dist: pyyaml (>=6.0,<7.0)
Requires-Dist: tabulate (>=0.9.0,<0.10.0)
Project-URL: Repository, https://github.com/aidanmelen/k4
